illustrate/__init__.py
illustrate/bot.py
illustrate/database.py
illustrate/hook.py
illustrate/scrape.py
illustrate/ui.py
illustrate-1.0.2.dist-info/LICENSE
illustrate-1.0.2.dist-info/METADATA
illustrate-1.0.2.dist-info/WHEEL
illustrate-1.0.2.dist-info/top_level.txt
illustrate-1.0.2.dist-info/RECORD
