Metadata-Version: 2.1
Name: illustrate
Version: 1.0.2
Summary: Simplistic & powerful crypto analytics
Home-page: https://github.com/m9m/illustrate
Author: m9m
License: MIT
Project-URL: Website, https://keeganm.net
Project-URL: Github, https://github.com/m9m/illustrate
Requires-Python: >=3.8.0
License-File: LICENSE
Requires-Dist: requests >=2.28.1
Requires-Dist: py-cord >=2.0.0
